<?xml version="1.0" encoding="UTF-8"?>
<objects serializationModel="Studio.02.02.00">
	<object class="AudioFile" id="{325e3f28-24bc-4a0f-8b2f-3ca07e0a6ae7}">
		<property name="assetPath">
			<value>MusicLoop/music_calm_tree_of_life.wav</value>
		</property>
		<property name="isStreaming">
			<value>true</value>
		</property>
		<property name="frequencyInKHz">
			<value>44.0999985</value>
		</property>
		<property name="channelCount">
			<value>2</value>
		</property>
		<property name="length">
			<value>144.22351473922902</value>
		</property>
		<relationship name="masterAssetFolder">
			<destination>{29f5aa69-bd8b-4fdc-8145-0cca53d26150}</destination>
		</relationship>
	</object>
</objects>
